cyclicredundancypython-0.1.0.data/scripts/cyc.py
src/__init__.py
src/cyc.py
cyclicredundancypython-0.1.0.dist-info/METADATA
cyclicredundancypython-0.1.0.dist-info/WHEEL
cyclicredundancypython-0.1.0.dist-info/entry_points.txt
cyclicredundancypython-0.1.0.dist-info/top_level.txt
cyclicredundancypython-0.1.0.dist-info/RECORD
