Metadata-Version: 2.1
Name: cyclicredundancypython
Version: 0.1.0
Summary: Cyclic redundancy check for the given data bits
Author: Thejas hari
Author-email: <thejaskala308@gmail.com>
Keywords: python,url,cyclic-redundance,encode,decode,cyc,cyc-encode-decode
Classifier: Development Status :: 1 - Planning
Classifier: Intended Audience :: Developers
Classifier: Programming Language :: Python :: 3
Classifier: Operating System :: Unix
Classifier: Operating System :: MacOS :: MacOS X
Classifier: Operating System :: Microsoft :: Windows
